slackops/__init__.py
slackops/blocks.py
slackops/interfaces.py
slackops/templates.py
slackops-0.1.7.dist-info/LICENSE
slackops-0.1.7.dist-info/METADATA
slackops-0.1.7.dist-info/WHEEL
slackops-0.1.7.dist-info/RECORD
