Metadata-Version: 2.1
Name: slackops
Version: 0.1.7
Summary: Easily post good looking slack messages about your operations
Author: Eremin
Author-email: haru.eaa@gmail.com
Requires-Python: >=3.9.0,<4.0.0
Classifier: Programming Language :: Python :: 3
Classifier: Programming Language :: Python :: 3.9
Classifier: Programming Language :: Python :: 3.10
Classifier: Programming Language :: Python :: 3.11
Requires-Dist: slack-sdk (>=3.20.1,<4.0.0)
